setup.cfg
setup.py
Gibberisch.egg-info/PKG-INFO
Gibberisch.egg-info/SOURCES.txt
Gibberisch.egg-info/dependency_links.txt
Gibberisch.egg-info/entry_points.txt
Gibberisch.egg-info/namespace_packages.txt
Gibberisch.egg-info/not-zip-safe
Gibberisch.egg-info/requires.txt
Gibberisch.egg-info/top_level.txt
gibberis/__init__.py
gibberis/ch/__init__.py
gibberis/ch/chomsky.py
gibberis/ch/freeform.py
