Metadata-Version: 1.0
Name: Gibberisch
Version: 0.1dev
Summary: Random text generator
Home-page: UNKNOWN
Author: UNKNOWN
Author-email: UNKNOWN
License: GPL
Platform: UNKNOWN
Classifier: Framework :: Plone
Classifier: Framework :: Zope2
Classifier: Framework :: Zope3
Classifier: Programming Language :: Python
Classifier: Topic :: Software Development :: Libraries :: Python Modules
